insilicosv/__init__.py
insilicosv/constants.py
insilicosv/processing.py
insilicosv/simulate.py
insilicosv/structural_variant.py
insilicosv/utils.py
insilicosv-0.0.6.dist-info/LICENSE
insilicosv-0.0.6.dist-info/METADATA
insilicosv-0.0.6.dist-info/WHEEL
insilicosv-0.0.6.dist-info/entry_points.txt
insilicosv-0.0.6.dist-info/top_level.txt
insilicosv-0.0.6.dist-info/RECORD
