Metadata-Version: 2.1
Name: insilicosv
Version: 0.0.6
Summary: Simulator of complex structural variants in genomes
Home-page: https://github.com/PopicLab/insilicoSV
Author-email: Chris Rohlicek <crohlice@broadinstitute.org>, Nick Jiang <nickj@berkeley.edu>, Ilya Shlyakhter <ilya@broadinstitute.org>, Victoria Popic <vpopic@broadinstitute.org>
License: MIT
Project-URL: Homepage, https://github.com/PopicLab/insilicoSV
Project-URL: Issues, https://github.com/PopicLab/insilicoSV/issues
Classifier: Programming Language :: Python :: 3
Classifier: License :: OSI Approved :: MIT License
Classifier: Operating System :: OS Independent
Requires-Python: >=3.8
License-File: LICENSE
Requires-Dist: cycler
Requires-Dist: kiwisolver
Requires-Dist: matplotlib
Requires-Dist: numpy
Requires-Dist: Pillow
Requires-Dist: pyparsing
Requires-Dist: pysam
Requires-Dist: python-dateutil
Requires-Dist: PyYAML
Requires-Dist: six
